petsafe_scoopfree/__init__.py
petsafe_scoopfree/__main__.py
petsafe_scoopfree/client.py
petsafe_scoopfree/devices.py
petsafe_scoopfree-0.0.1.dist-info/LICENSE
petsafe_scoopfree-0.0.1.dist-info/METADATA
petsafe_scoopfree-0.0.1.dist-info/WHEEL
petsafe_scoopfree-0.0.1.dist-info/top_level.txt
petsafe_scoopfree-0.0.1.dist-info/RECORD
