Metadata-Version: 2.1
Name: petsafe-scoopfree
Version: 0.0.1
Summary: Petsafe Scoopfree Integration
Home-page: https://github.com/crslen/petsafe_scoopfree
Author: Chris Lennon
Author-email: Chris Lennon <lennonc@gmail.com>
License: Copyright (c) 2020 Jordan Stremming        
Project-URL: Homepage, https://github.com/crslen/petsafe_scoopfree
Project-URL: Bug Tracker, https://github.com/crslen/petsafe_scoopfree/issues
Classifier: Programming Language :: Python :: 3
Classifier: License :: OSI Approved :: MIT License
Classifier: Operating System :: OS Independent
Requires-Python: >=3.6
License-File: LICENSE
Requires-Dist: requests
Requires-Dist: boto3
